synchronous FIFO/RTL/sync_fifo.v
module sync_fifo #(
  parameter WIDTH = 8,
  parameter DEPTH = 16
)(
  input clk,rst,
  input [WIDTH-1:0] data_in,
  output reg [WIDTH-1:0] data_out,
  input wr_en,
  input rd_en,
  output full,
  output empty,
  output reg [4:0] count
);
  localparam PTR_WIDTH = $clog2(DEPTH);
  reg [WIDTH-1:0] mem [DEPTH-1:0];
  reg [PTR_WIDTH:0] wr_ptr,rd_ptr;

  always @(posedge clk or negedge rst) begin
    if(!rst) begin
      data_out <= 0;
      wr_ptr <= 0;
      rd_ptr <= 0;
      count <= 0;
    end
    else begin
      if(wr_en && !full) begin
        mem[wr_ptr[PTR_WIDTH-1:0] % DEPTH] <= data_in;
        wr_ptr <= wr_ptr + 1;
        count +=1;
      end
      if(rd_en && !empty) begin
        data_out <= mem[rd_ptr[PTR_WIDTH-1:0] % DEPTH];
        rd_ptr <= rd_ptr + 1;
        count -= 1;
      end
    end
  end

  assign full = (wr_ptr - rd_ptr == DEPTH || rd_ptr - wr_ptr == DEPTH);
  assign empty = (wr_ptr == rd_ptr);

endmodule

synchronous FIFO/Verification/sync_fifo_tb.v
module syn_fifo_tb;

  parameter WIDTH = 16;
  parameter DEPTH = 10;
  parameter clkp = 40;

  // Inputs
  reg clk, rst;
  reg [WIDTH-1:0] data_in;
  reg write_en, read_en;

  // Outputs
  wire [WIDTH-1:0] data_out;
  wire full, empty;

  // Memory for data comparison
  reg [WIDTH-1:0] mem [0:DEPTH-1]; // Fixed-size array
  integer mem_head = 0; // Pointer for writing to the array
  integer mem_tail = 0; // Pointer for reading from the array

  // FIFO instance
  sync_fifo #(.WIDTH(WIDTH), .DEPTH(DEPTH)) s_fifo (
    .clk(clk),
    .rst(rst),
    .data_in(data_in),
    .data_out(data_out),  
    .wr_en(write_en),
    .rd_en(read_en),
    .full(full),
    .empty(empty)
  );

  // Clock generation
  always #(clkp / 2) clk = ~clk;

  // Test procedure
  initial begin
    // Initialize inputs
    clk = 0;
    rst = 0;
    data_in = 0;
    write_en = 0;
    read_en = 0;

    // Apply reset
    repeat(5) @(posedge clk);
    rst = 1;

    // Case 1: Write until FIFO is full
    @(negedge clk) write_en = 1;

    for (integer i = 0; i < DEPTH + 5; i = i + 1) begin
      @(posedge clk);
      data_in = $urandom % 256;
      if (!full && write_en) begin
        mem[mem_head] = data_in; // Store data in memory
        mem_head = (mem_head + 1) % DEPTH;
      end
    end
    write_en = 0;


    // Case 2: Read until FIFO is empty
    repeat(5) @(posedge clk);
    read_en = 1;

    for (integer j = 0; j < DEPTH + 5; j = j + 1) begin
      @(posedge clk);
      if (!empty && read_en) begin
        if (mem[mem_tail] == data_out)
          $display("Time = %0t: Comparison Passed: wr_data = %h and rd_data = %h", $time, mem[mem_tail], data_out);
        else
          $display("Time = %0t: Comparison Failed: expected wr_data = %h, rd_data = %h", $time, mem[mem_tail], data_out);
        mem_tail = (mem_tail + 1) % DEPTH;
      end
    end
    read_en = 0;

    // Case 3: Write and Read Alternating
    repeat(5) @(posedge clk);
    @(negedge clk) write_en = 1;
    read_en = 1;
    for (integer k = 0; k < DEPTH * 2; k = k + 1) begin
      @(posedge clk);
      data_in = $urandom % 256;
      if (!full && write_en) begin
        mem[mem_head] = data_in;
        mem_head = (mem_head + 1) % DEPTH;
      end
      if (!empty && read_en) begin
        if (mem[mem_tail] == data_out)
          $display("Time = %0t: Alternating R/W Passed: wr_data = %h and rd_data = %h", $time, mem[mem_tail], data_out);
        else
          $display("Time = %0t: Alternating R/W Failed: expected wr_data = %h, rd_data = %h", $time, mem[mem_tail], data_out);
        mem_tail = (mem_tail + 1) % DEPTH;
      end
    end
    @(negedge clk) write_en = 0;
    read_en = 0;

    // Case 4: Reset during operation
    repeat(5) @(posedge clk);
    @(negedge clk) rst = 0;
    repeat(5) @(posedge clk);
    @(negedge clk) rst = 1;

    // Final delay before ending simulation
    #1000;
    $finish;
  end

  // Dump waveforms
  initial begin
    $dumpfile("sync_fifo_tb.vcd");
    $dumpvars(0, syn_fifo_tb);
  end

endmodule

synchronous FIFO/Verification/sync_fifo_tb.vcd
$date
	Wed Apr 02 21:55:45 2025
$end
$version
	Icarus Verilog
$end
$timescale
	1s
$end
$scope module syn_fifo_tb $end
$var wire 1 ! full $end
$var wire 1 " empty $end
$var wire 16 # data_out [15:0] $end
$var reg 1 $ clk $end
$var reg 16 % data_in [15:0] $end
$var reg 1 & read_en $end
$var reg 1 ' rst $end
$var reg 1 ( write_en $end
$var integer 32 ) mem_head [31:0] $end
$var integer 32 * mem_tail [31:0] $end
$scope module s_fifo $end
$var wire 1 $ clk $end
$var wire 16 + data_in [15:0] $end
$var wire 1 ! full $end
$var wire 1 & rd_en $end
$var wire 1 ' rst $end
$var wire 1 ( wr_en $end
$var wire 1 " empty $end
$var reg 5 , count [4:0] $end
$var reg 16 - data_out [15:0] $end
$var reg 5 . rd_ptr [4:0] $end
$var reg 5 / wr_ptr [4:0] $end
$upscope $end
$scope begin $ivl_for_loop0 $end
$var integer 32 0 i [31:0] $end
$upscope $end
$scope begin $ivl_for_loop1 $end
$var integer 32 1 j [31:0] $end
$upscope $end
$scope begin $ivl_for_loop2 $end
$var integer 32 2 k [31:0] $end
$upscope $end
$upscope $end
$enddefinitions $end
#0
$dumpvars
bx 2
bx 1
bx 0
b0 /
b0 .
b0 -
b0 ,
b0 +
b0 *
b0 )
0(
0'
0&
b0 %
0$
b0 #
1"
0!
$end
#20
1$
#40
0$
#60
1$
#80
0$
#100
1$
#120
0$
#140
1$
#160
0$
#180
1'
1$
#200
b0 0
1(
0$
#220
0"
b1 /
b1 ,
b1 0
b1 )
b100100 %
b100100 +
1$
#240
0$
#260
b10 /
b10 ,
b10 0
b10 )
b10000001 %
b10000001 +
1$
#280
0$
#300
b11 /
b11 ,
b11 0
b11 )
b1001 %
b1001 +
1$
#320
0$
#340
b100 /
b100 ,
b100 0
b100 )
b1100011 %
b1100011 +
1$
#360
0$
#380
b101 /
b101 ,
b101 0
b101 )
b1101 %
b1101 +
1$
#400
0$
#420
b110 /
b110 ,
b110 0
b110 )
b10001101 %
b10001101 +
1$
#440
0$
#460
b111 /
b111 ,
b111 0
b111 )
b1100101 %
b1100101 +
1$
#480
0$
#500
b1000 /
b1000 ,
b1000 0
b1000 )
b10010 %
b10010 +
1$
#520
0$
#540
b1001 /
b1001 ,
b1001 0
b1001 )
b1 %
b1 +
1$
#560
0$
#580
1!
b1010 /
b1010 ,
b1010 0
b0 )
b1101 %
b1101 +
1$
#600
0$
#620
b1011 0
b1110110 %
b1110110 +
1$
#640
0$
#660
b1100 0
b111101 %
b111101 +
1$
#680
0$
#700
b1101 0
b11101101 %
b11101101 +
1$
#720
0$
#740
b1110 0
b10001100 %
b10001100 +
1$
#760
0$
#780
0(
b1111 0
b11111001 %
b11111001 +
1$
#800
0$
#820
1$
#840
0$
#860
1$
#880
0$
#900
1$
#920
0$
#940
1$
#960
0$
#980
0!
b1 .
b100100 #
b100100 -
b1001 ,
b0 1
1&
1$
#1000
0$
#1020
b10 .
b10000001 #
b10000001 -
b1000 ,
b1 1
b1 *
1$
#1040
0$
#1060
b11 .
b1001 #
b1001 -
b111 ,
b10 1
b10 *
1$
#1080
0$
#1100
b100 .
b1100011 #
b1100011 -
b110 ,
b11 1
b11 *
1$
#1120
0$
#1140
b101 .
b1101 #
b1101 -
b101 ,
b100 1
b100 *
1$
#1160
0$
#1180
b110 .
b10001101 #
b10001101 -
b100 ,
b101 1
b101 *
1$
#1200
0$
#1220
b111 .
b1100101 #
b1100101 -
b11 ,
b110 1
b110 *
1$
#1240
0$
#1260
b1000 .
b10010 #
b10010 -
b10 ,
b111 1
b111 *
1$
#1280
0$
#1300
b1001 .
b1 #
b1 -
b1 ,
b1000 1
b1000 *
1$
#1320
0$
#1340
1"
b1010 .
b1101 #
b1101 -
b0 ,
b1001 1
b1001 *
1$
#1360
0$
#1380
b1010 1
1$
#1400
0$
#1420
b1011 1
1$
#1440
0$
#1460
b1100 1
1$
#1480
0$
#1500
b1101 1
1$
#1520
0$
#1540
b1110 1
1$
#1560
0$
#1580
0&
b1111 1
1$
#1600
0$
#1620
1$
#1640
0$
#1660
1$
#1680
0$
#1700
1$
#1720
0$
#1740
1$
#1760
0$
#1780
1$
#1800
b0 2
1&
1(
0$
#1820
0"
b1011 /
b1 ,
b1 2
b1 )
b11000110 %
b11000110 +
1$
#1840
0$
#1860
b1011 .
b11000110 #
b11000110 -
b1100 /
b1 ,
b10 2
b0 *
b10 )
b11000101 %
b11000101 +
1$
#1880
0$
#1900
b1100 .
b11000101 #
b11000101 -
b1101 /
b1 ,
b11 2
b1 *
b11 )
b10101010 %
b10101010 +
1$
#1920
0$
#1940
b1101 .
b10101010 #
b10101010 -
b1110 /
b1 ,
b100 2
b10 *
b100 )
b11100101 %
b11100101 +
1$
#1960
0$
#1980
b1110 .
b11100101 #
b11100101 -
b1111 /
b1 ,
b101 2
b11 *
b101 )
b1110111 %
b1110111 +
1$
#2000
0$
#2020
b1111 .
b1110111 #
b1110111 -
b10000 /
b1 ,
b110 2
b100 *
b110 )
b10010 %
b10010 +
1$
#2040
0$
#2060
b10000 .
b10010 #
b10010 -
b10001 /
b1 ,
b111 2
b101 *
b111 )
b10001111 %
b10001111 +
1$
#2080
0$
#2100
b10001 .
b10001111 #
b10001111 -
b10010 /
b1 ,
b1000 2
b110 *
b1000 )
b11110010 %
b11110010 +
1$
#2120
0$
#2140
b10010 .
b11110010 #
b11110010 -
b10011 /
b1 ,
b1001 2
b111 *
b1001 )
b11001110 %
b11001110 +
1$
#2160
0$
#2180
b10011 .
b11001110 #
b11001110 -
b10100 /
b1 ,
b1010 2
b1000 *
b0 )
b11101000 %
b11101000 +
1$
#2200
0$
#2220
b10100 .
b11101000 #
b11101000 -
b10101 /
b1 ,
b1011 2
b1001 *
b1 )
b11000101 %
b11000101 +
1$
#2240
0$
#2260
b10101 .
b11000101 #
b11000101 -
b10110 /
b1 ,
b1100 2
b0 *
b10 )
b1011100 %
b1011100 +
1$
#2280
0$
#2300
b10110 .
b1011100 #
b1011100 -
b10111 /
b1 ,
b1101 2
b1 *
b11 )
b10111101 %
b10111101 +
1$
#2320
0$
#2340
b10111 .
b10111101 #
b10111101 -
b11000 /
b1 ,
b1110 2
b10 *
b100 )
b101101 %
b101101 +
1$
#2360
0$
#2380
b11000 .
b101101 #
b101101 -
b11001 /
b1 ,
b1111 2
b11 *
b101 )
b1100101 %
b1100101 +
1$
#2400
0$
#2420
b11001 .
b1100101 #
b1100101 -
b11010 /
b1 ,
b10000 2
b100 *
b110 )
b1100011 %
b1100011 +
1$
#2440
0$
#2460
b11010 .
b1100011 #
b1100011 -
b11011 /
b1 ,
b10001 2
b101 *
b111 )
b1010 %
b1010 +
1$
#2480
0$
#2500
b11011 .
b1010 #
b1010 -
b11100 /
b1 ,
b10010 2
b110 *
b1000 )
b10000000 %
b10000000 +
1$
#2520
0$
#2540
b11100 .
b10000000 #
b10000000 -
b11101 /
b1 ,
b10011 2
b111 *
b1001 )
b100000 %
b100000 +
1$
#2560
0$
#2580
b11101 .
b100000 #
b100000 -
b11110 /
b1 ,
b10100 2
b1000 *
b0 )
b10101010 %
b10101010 +
1$
#2600
0&
0(
0$
#2620
1$
#2640
0$
#2660
1$
#2680
0$
#2700
1$
#2720
0$
#2740
1$
#2760
0$
#2780
1$
#2800
b0 ,
1"
b0 .
b0 /
b0 #
b0 -
0'
0$
#2820
1$
#2840
0$
#2860
1$
#2880
0$
#2900
1$
#2920
0$
#2940
1$
#2960
0$
#2980
1$
#3000
1'
0$
