asynchronous FIFO/RTL/checkEmpty.v
module checkEmpty #(
  parameter WIDTH = 16,
  parameter PTR_WIDTH = 4
)(
  input rd_clk, rd_rst,
  input rd_en,
  input [PTR_WIDTH:0] wr_ptr_sync,
  output [PTR_WIDTH-1:0] rd_addr,
  output reg [PTR_WIDTH:0] rd_ptr_gray,
  output empty
);
  reg [PTR_WIDTH:0] rd_ptr_bin;
  wire [PTR_WIDTH:0] rd_ptr_next, rd_ptr_gray_next;
  wire [PTR_WIDTH:0] wr_ptr_bin;

// Chuyển mã Gray thành nhị phân
  function [PTR_WIDTH:0] gray_to_binary;
    input [PTR_WIDTH:0] gray;
    integer i;
    begin
      gray_to_binary[PTR_WIDTH] = gray[PTR_WIDTH]; // MSB giữ nguyên
      for (i = PTR_WIDTH-1; i >= 0; i = i - 1)
        gray_to_binary[i] = gray_to_binary[i+1] ^ gray[i];
    end
  endfunction

  always @(posedge rd_clk or negedge rd_rst) begin
    if (!rd_rst) begin
      rd_ptr_bin <= 0;
    end
    else begin
      if (rd_en && !empty) begin
        rd_ptr_bin <= rd_ptr_next;
      end
    end
  end

  always @(posedge rd_clk or negedge rd_rst) begin
    if(!rd_rst) begin
      rd_ptr_gray <= 0;
    end
    else begin
      rd_ptr_gray <= rd_ptr_gray_next;
    end
  end

  assign rd_ptr_next = rd_ptr_bin + (rd_en && !empty);
  assign rd_ptr_gray_next = (rd_ptr_next >> 1) ^ rd_ptr_next;
  assign rd_addr = rd_ptr_bin[PTR_WIDTH-1:0];

  // Chuyển wr_ptr_sync (Gray) thành wr_ptr_bin (Binary)
  assign wr_ptr_bin = gray_to_binary(wr_ptr_sync);

  // Kiểm tra trạng thái empty
  assign empty = (rd_ptr_bin == wr_ptr_bin) ? 1'b1 : 1'b0;


endmodule

asynchronous FIFO/RTL/checkFull.v

module checkFull #(
  parameter WIDTH = 16,
  parameter PTR_WIDTH = 4
)(
  input wr_clk, wr_rst,
  input wr_en,
  input [PTR_WIDTH:0] rd_ptr_sync,
  output [PTR_WIDTH-1:0] wr_addr,
  output reg [PTR_WIDTH:0] wr_ptr_gray,
  output full
);
  
  reg [PTR_WIDTH:0] wr_ptr_bin;
  wire [PTR_WIDTH:0] wr_ptr_next, wr_ptr_gray_next;
  wire [PTR_WIDTH:0] rd_ptr_bin;

  // Chuyển mã Gray thành nhị phân
  function [PTR_WIDTH:0] gray_to_binary;
    input [PTR_WIDTH:0] gray;
    integer i;
    begin
      gray_to_binary[PTR_WIDTH] = gray[PTR_WIDTH]; // MSB giữ nguyên
      for (i = PTR_WIDTH-1; i >= 0; i = i - 1)
        gray_to_binary[i] = gray_to_binary[i+1] ^ gray[i];
    end
  endfunction

  always @(posedge wr_clk or negedge wr_rst) begin
    if (!wr_rst) begin
      wr_ptr_bin <= 0;
    end else begin
      if (wr_en && !full) begin
        wr_ptr_bin <= wr_ptr_next;
      end
    end
  end

  always @(posedge wr_clk or negedge wr_rst) begin
    if (!wr_rst) begin
      wr_ptr_gray <= 0;
    end else begin
      wr_ptr_gray <= wr_ptr_gray_next;
    end
  end

  assign wr_ptr_next = wr_ptr_bin + (wr_en && !full);
  assign wr_ptr_gray_next = (wr_ptr_next >> 1) ^ wr_ptr_next;
  assign wr_addr = wr_ptr_bin[PTR_WIDTH-1:0];

  // Chuyển rd_ptr_sync (Gray) thành rd_ptr_bin (Binary)
  assign rd_ptr_bin = gray_to_binary(rd_ptr_sync);

  // Kiểm tra trạng thái full
  assign full = (wr_ptr_bin == {~rd_ptr_bin[PTR_WIDTH], rd_ptr_bin[PTR_WIDTH-1:0]}) ? 1'b1 : 1'b0;

endmodule

asynchronous FIFO/RTL/sync_2flops.v
module sync_2flops #(
  parameter PTR_WIDTH = 4
) (
  input clk, rst,
  input [PTR_WIDTH:0] data_in,
  output reg [PTR_WIDTH:0] data_out
);

  reg [PTR_WIDTH:0] data_out_1;
  always @(posedge clk or negedge rst) begin
    if(!rst) begin
      data_out <= 0;
      data_out_1 <= 0;
    end else begin
      data_out_1 <= data_in;
      data_out <= data_out_1;
    end
  end
endmodule

asynchronous FIFO/RTL/fifomem.v
module fifomem #(
  parameter WIDTH = 16,
  parameter DEPTH = 16
) (
  input wr_clk, wr_rst,
  input rd_clk, rd_rst,
  input [WIDTH-1:0] data_in,
  input wr_en,
  input rd_en,
  input full,
  input empty,
  input [PTR_WIDTH-1:0] wr_ptr,
  input [PTR_WIDTH-1:0] rd_ptr,
  output reg [WIDTH-1:0] data_out
);
  localparam PTR_WIDTH = $clog2(DEPTH);
  reg [WIDTH-1:0] mem [DEPTH-1:0];

  always @(posedge wr_clk) begin
    if(wr_en && !full) begin
      mem[wr_ptr] <= data_in;
    end
  end

  
  always @(posedge rd_clk) begin
    if(rd_en && !empty) begin
      data_out <= mem[rd_ptr];
    end
  end


endmodule

asynchronous FIFO/RTL/async_fifo.v
module async_fifo #(
  parameter WIDTH = 16,
  parameter DEPTH = 16
) (
  input wr_clk, wr_rst,
  input rd_clk, rd_rst,
  input [WIDTH-1:0] data_in,
  input wr_en,
  input rd_en,
  output [WIDTH-1:0] data_out,
  output full,
  output empty
);
  localparam PTR_WIDTH = $clog2(DEPTH);

wire [PTR_WIDTH:0] wr_ptr_gray, rd_ptr_gray;
wire [PTR_WIDTH:0] wr_ptr_sync, rd_ptr_sync;
wire [PTR_WIDTH-1:0] wr_ptr, rd_ptr;

fifomem #(
  .WIDTH(WIDTH),
  .DEPTH(DEPTH)
) mem (
  .wr_clk(wr_clk),
  .wr_rst(wr_rst),
  .rd_clk(rd_clk),
  .rd_rst(rd_rst),
  .data_in(data_in),
  .wr_en(wr_en),
  .rd_en(rd_en),
  .full(full),
  .empty(empty),
  .wr_ptr(wr_ptr),
  .rd_ptr(rd_ptr),
  .data_out(data_out)
);

sync_2flops #(
  .PTR_WIDTH(PTR_WIDTH)
) sync_2flops_wr (
  .clk(wr_clk),
  .rst(wr_rst),
  .data_in(rd_ptr_gray),
  .data_out(rd_ptr_sync)
);

sync_2flops #(
  .PTR_WIDTH(PTR_WIDTH)
) sync_2flops_rd (
  .clk(rd_clk),
  .rst(rd_rst),
  .data_in(wr_ptr_gray),
  .data_out(wr_ptr_sync)
);

checkFull #(
  .WIDTH(WIDTH),
  .PTR_WIDTH(PTR_WIDTH)
) wr_Full (
  .wr_clk(wr_clk),
  .wr_rst(wr_rst),
  .wr_en(wr_en),
  .rd_ptr_sync(rd_ptr_sync),
  .wr_addr(wr_ptr),
  .wr_ptr_gray(wr_ptr_gray),
  .full(full)
);


checkEmpty #(
  .WIDTH(WIDTH),
  .PTR_WIDTH(PTR_WIDTH)
) rd_empty (
  .rd_clk(rd_clk),
  .rd_rst(rd_rst),
  .rd_en(rd_en),
  .wr_ptr_sync(wr_ptr_sync),
  .rd_addr(rd_ptr),
  .rd_ptr_gray(rd_ptr_gray),
  .empty(empty)
);



endmodule

asynchronous FIFO/Verification/async_fifo_tb.v
`timescale 1ns/1ps

module async_fifo_tb;

  parameter WIDTH = 4;
  parameter DEPTH = 8;

  // Clock and reset signals
  reg wr_clk, rd_clk;
  reg wr_rst, rd_rst;
  reg wr_en, rd_en;

  // Data signals
  reg [WIDTH-1:0] data_in;
  wire [WIDTH-1:0] data_out;
  wire full, empty;


  // Instantiate the FIFO
  async_fifo #(
    .WIDTH(WIDTH),
    .DEPTH(DEPTH)
  ) uut (
    .wr_clk(wr_clk),
    .wr_rst(wr_rst),
    .wr_en(wr_en),
    .data_in(data_in),
    .full(full),

    .rd_clk(rd_clk),
    .rd_rst(rd_rst),
    .rd_en(rd_en),
    .data_out(data_out),
    .empty(empty)
  );

  // Clock generation
  always #10 wr_clk = ~wr_clk;  // Write clock with a 20ns period
  always #16 rd_clk = ~rd_clk;  // Read clock with a 60ns period

  // Task: Write data into FIFO and store in expected_data
  task write_fifo(input integer num_writes);
    integer i;
    begin
      for (i = 0; i < num_writes; i = i + 1) begin
        @(negedge wr_clk);
        if (!full) begin
          wr_en = 1;
          data_in = $urandom % 16;
          $display("Time = %t: Writing data: %d", $time, data_in);
        end else begin
          $display("Time = %t: FIFO full, cannot write!", $time);
          wr_en = 0;
        end
      end
    end
  endtask

  // Task: Read data from FIFO and compare with expected_data
  task read_fifo(input integer num_reads);
    integer i;
    begin
      for (i = 0; i < num_reads; i = i + 1) begin
        @(negedge rd_clk);
        if (!empty) begin
          rd_en = 1;
          $display("Time = %t: Data out: %d", $time, data_out);
        end else begin
          $display("Time = %t: FIFO empty, cannot read!", $time);
          rd_en = 0;
        end
      end
    end
  endtask

  initial begin
    // Initialize signals
    wr_clk = 0;
    rd_clk = 0;
    wr_rst = 0;
    rd_rst = 0;
    wr_en = 0;
    rd_en = 0;
    data_in = 0;


    // Apply reset
    #50;
    wr_rst = 0;
    rd_rst = 0;

    #30;
    wr_rst = 1;
    rd_rst = 1;

    #20;

    // Test scenario: Normal operation
    $display("Starting normal operation test...");
    write_fifo(DEPTH+2); // write full
    read_fifo(DEPTH+4); // read full
    #50;
    //Simultaneous write and read
    fork
    write_fifo(DEPTH+8); // write full
    read_fifo(DEPTH+4); // read full
    join

    // End simulation
    $display("All tests completed.");
    #200;
    $finish;
  end

  // Waveform generation
  initial begin
    $dumpfile("async_fifo_tb.vcd");
    $dumpvars(0, async_fifo_tb);
  end

endmodule

asynchronous FIFO/Verification/async_fifo_tb.vcd
$date
	Wed Apr 02 21:51:43 2025
$end
$version
	Icarus Verilog
$end
$timescale
	1ps
$end
$scope module async_fifo_tb $end
$var wire 1 ! full $end
$var wire 1 " empty $end
$var wire 4 # data_out [3:0] $end
$var reg 4 $ data_in [3:0] $end
$var reg 1 % rd_clk $end
$var reg 1 & rd_en $end
$var reg 1 ' rd_rst $end
$var reg 1 ( wr_clk $end
$var reg 1 ) wr_en $end
$var reg 1 * wr_rst $end
$scope module uut $end
$var wire 4 + data_in [3:0] $end
$var wire 1 % rd_clk $end
$var wire 1 & rd_en $end
$var wire 1 ' rd_rst $end
$var wire 1 ( wr_clk $end
$var wire 1 ) wr_en $end
$var wire 1 * wr_rst $end
$var wire 4 , wr_ptr_sync [3:0] $end
$var wire 4 - wr_ptr_gray [3:0] $end
$var wire 3 . wr_ptr [2:0] $end
$var wire 4 / rd_ptr_sync [3:0] $end
$var wire 4 0 rd_ptr_gray [3:0] $end
$var wire 3 1 rd_ptr [2:0] $end
$var wire 1 ! full $end
$var wire 1 " empty $end
$var wire 4 2 data_out [3:0] $end
$scope module mem $end
$var wire 4 3 data_in [3:0] $end
$var wire 1 % rd_clk $end
$var wire 1 & rd_en $end
$var wire 1 ' rd_rst $end
$var wire 1 ( wr_clk $end
$var wire 1 ) wr_en $end
$var wire 1 * wr_rst $end
$var wire 3 4 wr_ptr [2:0] $end
$var wire 3 5 rd_ptr [2:0] $end
$var wire 1 ! full $end
$var wire 1 " empty $end
$var reg 4 6 data_out [3:0] $end
$upscope $end
$scope module rd_empty $end
$var wire 1 % rd_clk $end
$var wire 1 & rd_en $end
$var wire 4 7 rd_ptr_gray_next [3:0] $end
$var wire 1 ' rd_rst $end
$var wire 4 8 wr_ptr_sync [3:0] $end
$var wire 4 9 wr_ptr_bin [3:0] $end
$var wire 4 : rd_ptr_next [3:0] $end
$var wire 3 ; rd_addr [2:0] $end
$var wire 1 " empty $end
$var reg 4 < rd_ptr_bin [3:0] $end
$var reg 4 = rd_ptr_gray [3:0] $end
$scope function gray_to_binary $end
$var reg 4 > gray [3:0] $end
$var integer 32 ? i [31:0] $end
$upscope $end
$upscope $end
$scope module sync_2flops_rd $end
$var wire 1 % clk $end
$var wire 1 ' rst $end
$var wire 4 @ data_in [3:0] $end
$var reg 4 A data_out [3:0] $end
$var reg 4 B data_out_1 [3:0] $end
$upscope $end
$scope module sync_2flops_wr $end
$var wire 1 ( clk $end
$var wire 4 C data_in [3:0] $end
$var wire 1 * rst $end
$var reg 4 D data_out [3:0] $end
$var reg 4 E data_out_1 [3:0] $end
$upscope $end
$scope module wr_Full $end
$var wire 4 F rd_ptr_sync [3:0] $end
$var wire 1 ( wr_clk $end
$var wire 1 ) wr_en $end
$var wire 4 G wr_ptr_gray_next [3:0] $end
$var wire 1 * wr_rst $end
$var wire 4 H wr_ptr_next [3:0] $end
$var wire 3 I wr_addr [2:0] $end
$var wire 4 J rd_ptr_bin [3:0] $end
$var wire 1 ! full $end
$var reg 4 K wr_ptr_bin [3:0] $end
$var reg 4 L wr_ptr_gray [3:0] $end
$scope function gray_to_binary $end
$var reg 4 M gray [3:0] $end
$var integer 32 N i [31:0] $end
$upscope $end
$upscope $end
$upscope $end
$scope task read_fifo $end
$var integer 32 O i [31:0] $end
$var integer 32 P num_reads [31:0] $end
$upscope $end
$scope task write_fifo $end
$var integer 32 Q i [31:0] $end
$var integer 32 R num_writes [31:0] $end
$upscope $end
$upscope $end
$enddefinitions $end
#0
$dumpvars
bx R
bx Q
bx P
bx O
b11111111111111111111111111111111 N
b0 M
b0 L
b0 K
b0 J
b0 I
b0 H
b0 G
b0 F
b0 E
b0 D
b0 C
b0 B
b0 A
b0 @
b11111111111111111111111111111111 ?
b0 >
b0 =
b0 <
b0 ;
b0 :
b0 9
b0 8
b0 7
bx 6
b0 5
b0 4
b0 3
bx 2
b0 1
b0 0
b0 /
b0 .
b0 -
b0 ,
b0 +
0*
0)
0(
0'
0&
0%
b0 $
bx #
1"
0!
$end
#10000
1(
#16000
1%
#20000
0(
#30000
1(
#32000
0%
#40000
0(
#48000
1%
#50000
1(
#60000
0(
#64000
0%
#70000
1(
#80000
0(
1%
1'
1*
#90000
1(
#96000
0%
#100000
b1 G
b1 H
b100 $
b100 +
b100 3
1)
0(
b1 Q
b1010 R
#110000
b11 G
b1 .
b1 4
b1 I
b10 H
b1 K
b1 -
b1 @
b1 L
1(
#112000
b1 B
1%
#120000
b10 Q
b1 $
b1 +
b1 3
0(
#128000
0%
#130000
b10 G
b10 .
b10 4
b10 I
b11 -
b11 @
b11 L
b11 H
b10 K
1(
#140000
b11 Q
b1001 $
b1001 +
b1001 3
0(
#144000
0"
b1 9
b11111111111111111111111111111111 ?
b1 >
b1 ,
b1 8
b1 A
b11 B
1%
#150000
b110 G
b11 .
b11 4
b11 I
b100 H
b11 K
b10 -
b10 @
b10 L
1(
#160000
b100 Q
b11 $
b11 +
b11 3
0(
0%
#170000
b111 G
b100 .
b100 4
b100 I
b110 -
b110 @
b110 L
b101 H
b100 K
1(
#176000
b10 9
b11111111111111111111111111111111 ?
b11 >
b11 ,
b11 8
b11 A
b110 B
1%
#180000
b101 Q
b1101 $
b1101 +
b1101 3
0(
#190000
b101 G
b101 .
b101 4
b101 I
b110 H
b101 K
b111 -
b111 @
b111 L
1(
#192000
0%
#200000
b110 Q
0(
#208000
b100 9
b11111111111111111111111111111111 ?
b110 >
b110 ,
b110 8
b110 A
b111 B
1%
#210000
b100 G
b110 .
b110 4
b110 I
b101 -
b101 @
b101 L
b111 H
b110 K
1(
#220000
b111 Q
b101 $
b101 +
b101 3
0(
#224000
0%
#230000
b1100 G
b111 .
b111 4
b111 I
b1000 H
b111 K
b100 -
b100 @
b100 L
1(
#240000
b101 9
b11111111111111111111111111111111 ?
b111 >
b111 ,
b111 8
b111 A
b100 B
b1000 Q
b10 $
b10 +
b10 3
0(
1%
#250000
b1100 G
b0 .
b0 4
b0 I
1!
b1100 -
b1100 @
b1100 L
b1000 H
b1000 K
1(
#256000
0%
#260000
b1001 Q
0)
0(
#270000
1(
#272000
b111 9
b11111111111111111111111111111111 ?
b100 >
b100 ,
b100 8
b100 A
b1100 B
1%
#280000
b0 O
b1100 P
b1010 Q
0(
#288000
b1 7
b1 :
b1 O
1&
0%
#290000
1(
#300000
0(
#304000
b1000 9
b11111111111111111111111111111111 ?
b1100 >
b11 7
b1 1
b1 5
b1 ;
b100 #
b100 2
b100 6
b1100 ,
b1100 8
b1100 A
b10 :
b1 <
b1 0
b1 =
b1 C
1%
#310000
b1 E
1(
#320000
b10 O
0(
0%
#330000
0!
b1 J
b11111111111111111111111111111111 N
b1 M
b1 /
b1 D
b1 F
1(
#336000
b10 7
b10 1
b10 5
b10 ;
b1 #
b1 2
b1 6
b11 0
b11 =
b11 C
b11 :
b10 <
1%
#340000
0(
#350000
b11 E
1(
#352000
b11 O
0%
#360000
0(
#368000
b110 7
b11 1
b11 5
b11 ;
b1001 #
b1001 2
b1001 6
b100 :
b11 <
b10 0
b10 =
b10 C
1%
#370000
b10 J
b11111111111111111111111111111111 N
b11 M
b11 /
b11 D
b11 F
b10 E
1(
#380000
0(
#384000
b100 O
0%
#390000
b11 J
b11111111111111111111111111111111 N
b10 M
b10 /
b10 D
b10 F
1(
#400000
b111 7
b100 1
b100 5
b100 ;
b11 #
b11 2
b11 6
b110 0
b110 =
b110 C
b101 :
b100 <
0(
1%
#410000
b110 E
1(
#416000
b101 O
0%
#420000
0(
#430000
b100 J
b11111111111111111111111111111111 N
b110 M
b110 /
b110 D
b110 F
1(
#432000
b101 7
b101 1
b101 5
b101 ;
b1101 #
b1101 2
b1101 6
b110 :
b101 <
b111 0
b111 =
b111 C
1%
#440000
0(
#448000
b110 O
0%
#450000
b111 E
1(
#460000
0(
#464000
b100 7
b110 1
b110 5
b110 ;
b101 0
b101 =
b101 C
b111 :
b110 <
1%
#470000
b101 J
b11111111111111111111111111111111 N
b111 M
b111 /
b111 D
b111 F
b101 E
1(
#480000
b111 O
0(
0%
#490000
b110 J
b11111111111111111111111111111111 N
b101 M
b101 /
b101 D
b101 F
1(
#496000
b1100 7
b111 1
b111 5
b111 ;
b101 #
b101 2
b101 6
b1000 :
b111 <
b100 0
b100 =
b100 C
1%
#500000
0(
#510000
b100 E
1(
#512000
b1000 O
0%
#520000
0(
#528000
b1100 7
b0 1
b0 5
b0 ;
1"
b10 #
b10 2
b10 6
b1100 0
b1100 =
b1100 C
b1000 :
b1000 <
1%
#530000
b111 J
b11111111111111111111111111111111 N
b100 M
b100 /
b100 D
b100 F
b1100 E
1(
#540000
0(
#544000
b1001 O
0&
0%
#550000
0!
b1000 J
b11111111111111111111111111111111 N
b1100 M
b1100 /
b1100 D
b1100 F
1(
#560000
0(
1%
#570000
1(
#576000
b1010 O
0%
#580000
0(
#590000
1(
#592000
1%
#600000
0(
#608000
b1011 O
0%
#610000
1(
#620000
0(
#624000
1%
#630000
1(
#640000
b1100 O
0(
0%
#650000
1(
#656000
1%
#660000
0(
#670000
1(
#672000
0%
#680000
0(
#688000
1%
#690000
1(
b0 Q
b10000 R
b0 O
#700000
b1101 G
b1001 H
b1 Q
b1 $
b1 +
b1 3
1)
0(
#704000
b1 O
0%
#710000
b1111 G
b1 .
b1 4
b1 I
b1010 H
b1001 K
b1101 -
b1101 @
b1101 L
1(
#720000
b1101 B
b10 Q
b1101 $
b1101 +
b1101 3
0(
1%
#730000
b1110 G
b10 .
b10 4
b10 I
b1111 -
b1111 @
b1111 L
b1011 H
b1010 K
1(
#736000
b10 O
0%
#740000
b11 Q
b110 $
b110 +
b110 3
0(
#750000
b1010 G
b11 .
b11 4
b11 I
b1100 H
b1011 K
b1110 -
b1110 @
b1110 L
1(
#752000
0"
b1001 9
b11111111111111111111111111111111 ?
b1101 >
b1101 ,
b1101 8
b1101 A
b1110 B
1%
#760000
b100 Q
b1101 $
b1101 +
b1101 3
0(
#768000
b1101 7
b1001 :
b11 O
1&
0%
#770000
b1011 G
b100 .
b100 4
b100 I
b1010 -
b1010 @
b1010 L
b1101 H
b1100 K
1(
#780000
b101 Q
0(
#784000
b1111 7
b1 1
b1 5
b1 ;
b1011 9
b11111111111111111111111111111111 ?
b1110 >
b1 #
b1 2
b1 6
b1101 0
b1101 =
b1101 C
b1010 :
b1001 <
b1110 ,
b1110 8
b1110 A
b1010 B
1%
#790000
b1001 G
b101 .
b101 4
b101 I
b1101 E
b1110 H
b1101 K
b1011 -
b1011 @
b1011 L
1(
#800000
b110 Q
b1100 $
b1100 +
b1100 3
b100 O
0(
0%
#810000
b1000 G
b110 .
b110 4
b110 I
b1001 J
b11111111111111111111111111111111 N
b1101 M
b1001 -
b1001 @
b1001 L
b1111 H
b1110 K
b1101 /
b1101 D
b1101 F
1(
#816000
b1100 9
b11111111111111111111111111111111 ?
b1010 >
b1110 7
b10 1
b10 5
b10 ;
b1101 #
b1101 2
b1101 6
b1010 ,
b1010 8
b1010 A
b1001 B
b1011 :
b1010 <
b1111 0
b1111 =
b1111 C
1%
#820000
b111 Q
b1001 $
b1001 +
b1001 3
0(
#830000
b0 G
b111 .
b111 4
b111 I
b1111 E
b0 H
b1111 K
b1000 -
b1000 @
b1000 L
1(
#832000
b101 O
0%
#840000
b1000 Q
b110 $
b110 +
b110 3
0(
#848000
b1010 7
b11 1
b11 5
b11 ;
b1110 9
b11111111111111111111111111111111 ?
b1001 >
b110 #
b110 2
b110 6
b1110 0
b1110 =
b1110 C
b1100 :
b1011 <
b1001 ,
b1001 8
b1001 A
b1000 B
1%
#850000
b1 G
b0 .
b0 4
b0 I
b1010 J
b11111111111111111111111111111111 N
b1111 M
b0 -
b0 @
b0 L
b1 H
b0 K
b1111 /
b1111 D
b1111 F
b1110 E
1(
#860000
b1001 Q
b101 $
b101 +
b101 3
0(
#864000
b110 O
0%
#870000
b1011 J
b11111111111111111111111111111111 N
b1110 M
b11 G
b1 .
b1 4
b1 I
b1110 /
b1110 D
b1110 F
b10 H
b1 K
b1 -
b1 @
b1 L
1(
#880000
b1111 9
b11111111111111111111111111111111 ?
b1000 >
b1011 7
b100 1
b100 5
b100 ;
b1101 #
b1101 2
b1101 6
b1000 ,
b1000 8
b1000 A
b1 B
b1101 :
b1100 <
b1010 0
b1010 =
b1010 C
b1010 Q
b1010 $
b1010 +
b1010 3
0(
1%
#890000
b10 G
b10 .
b10 4
b10 I
b11 -
b11 @
b11 L
b11 H
b10 K
b1010 E
1(
#896000
b111 O
0%
#900000
b1011 Q
b101 $
b101 +
b101 3
0(
#910000
b1100 J
b11111111111111111111111111111111 N
b1010 M
b110 G
b11 .
b11 4
b11 I
0!
b1010 /
b1010 D
b1010 F
b100 H
b11 K
b10 -
b10 @
b10 L
1(
#912000
b1001 7
b101 1
b101 5
b101 ;
b1 9
b11111111111111111111111111111111 ?
b1 >
b1011 0
b1011 =
b1011 C
b1110 :
b1101 <
b1 ,
b1 8
b1 A
b10 B
1%
#920000
b1100 Q
b111 $
b111 +
b111 3
0(
#928000
b1000 O
0%
#930000
b110 G
b100 .
b100 4
b100 I
1!
b110 -
b110 @
b110 L
b100 H
b100 K
b1011 E
1(
#940000
b1101 Q
0)
0(
#944000
b11 9
b11111111111111111111111111111111 ?
b10 >
b1000 7
b110 1
b110 5
b110 ;
b1100 #
b1100 2
b1100 6
b10 ,
b10 8
b10 A
b110 B
b1111 :
b1110 <
b1001 0
b1001 =
b1001 C
1%
#950000
0!
b1101 J
b11111111111111111111111111111111 N
b1011 M
b1011 /
b1011 D
b1011 F
b1001 E
1(
#960000
b111 G
b101 H
b1110 Q
b10 $
b10 +
b10 3
1)
b1001 O
0(
0%
#970000
b101 G
b101 .
b101 4
b101 I
0!
b1110 J
b11111111111111111111111111111111 N
b1001 M
b111 -
b111 @
b111 L
b110 H
b101 K
b1001 /
b1001 D
b1001 F
1(
#976000
b0 7
b111 1
b111 5
b111 ;
b100 9
b11111111111111111111111111111111 ?
b110 >
b1001 #
b1001 2
b1001 6
b1000 0
b1000 =
b1000 C
b0 :
b1111 <
b110 ,
b110 8
b110 A
b111 B
1%
#980000
b1111 Q
b1111 $
b1111 +
b1111 3
0(
#990000
b101 G
b110 .
b110 4
b110 I
1!
b1000 E
b110 H
b110 K
b101 -
b101 @
b101 L
1(
#992000
b1010 O
0%
#1000000
b10000 Q
0)
0(
#1008000
b101 9
b11111111111111111111111111111111 ?
b111 >
b1 7
b0 1
b0 5
b0 ;
b110 #
b110 2
b110 6
b111 ,
b111 8
b111 A
b101 B
b1 :
b0 <
b0 0
b0 =
b0 C
1%
#1010000
0!
b1111 J
b11111111111111111111111111111111 N
b1000 M
b1000 /
b1000 D
b1000 F
b0 E
1(
#1020000
0(
#1024000
b1011 O
0%
#1030000
b0 J
b11111111111111111111111111111111 N
b0 M
b0 /
b0 D
b0 F
1(
#1040000
b11 7
b1 1
b1 5
b1 ;
b110 9
b11111111111111111111111111111111 ?
b101 >
b101 #
b101 2
b101 6
b1 0
b1 =
b1 C
b10 :
b1 <
b101 ,
b101 8
b101 A
0(
1%
#1050000
b1 E
1(
#1056000
b1100 O
0%
#1060000
0(
#1070000
b1 J
b11111111111111111111111111111111 N
b1 M
b1 /
b1 D
b1 F
1(
#1072000
b10 7
b10 1
b10 5
b10 ;
b1010 #
b1010 2
b1010 6
b11 :
b10 <
b11 0
b11 =
b11 C
1%
#1080000
0(
#1088000
0%
#1090000
b11 E
1(
#1100000
0(
#1104000
b110 7
b11 1
b11 5
b11 ;
b101 #
b101 2
b101 6
b10 0
b10 =
b10 C
b100 :
b11 <
1%
#1110000
b10 J
b11111111111111111111111111111111 N
b11 M
b11 /
b11 D
b11 F
b10 E
1(
#1120000
0(
0%
#1130000
b11 J
b11111111111111111111111111111111 N
b10 M
b10 /
b10 D
b10 F
1(
#1136000
b111 7
b100 1
b100 5
b100 ;
b111 #
b111 2
b111 6
b101 :
b100 <
b110 0
b110 =
b110 C
1%
#1140000
0(
#1150000
b110 E
1(
#1152000
0%
#1160000
0(
#1168000
b101 7
b101 1
b101 5
b101 ;
b10 #
b10 2
b10 6
b111 0
b111 =
b111 C
b110 :
b101 <
1%
#1170000
b100 J
b11111111111111111111111111111111 N
b110 M
b110 /
b110 D
b110 F
b111 E
1(
#1180000
0(
#1184000
0%
#1190000
b101 J
b11111111111111111111111111111111 N
b111 M
b111 /
b111 D
b111 F
1(
#1200000
b101 7
b110 1
b110 5
b110 ;
1"
b1111 #
b1111 2
b1111 6
b110 :
b110 <
b101 0
b101 =
b101 C
0(
1%
#1210000
b101 E
1(
#1216000
0%
#1220000
0(
#1230000
b110 J
b11111111111111111111111111111111 N
b101 M
b101 /
b101 D
b101 F
1(
